itchi/__init__.py
itchi/config.py
itchi/config_attrs_doc.py
itchi/itchi_cli.py
itchi/itchi_gui.py
itchi/preprocess.py
itchi/signals.py
itchi/type_enum.py
itchi/gui/__init__.py
itchi/gui/controller.py
itchi/gui/iTCHi_GUI.ui
itchi/gui/icon.png
itchi/gui/models.py
itchi/inspectors/__init__.py
itchi/inspectors/formula_resolver.py
itchi/inspectors/isr.py
itchi/inspectors/objects.py
itchi/inspectors/state_resolver.py
itchi/inspectors/taskstate.py
itchi/ortilib/__init__.py
itchi/ortilib/formula.py
itchi/ortilib/formula_parser.py
itchi/ortilib/formula_scanner.py
itchi/ortilib/orti.py
itchi/ortilib/orti_parser.py
itchi/ortilib/orti_scanner.py
itchi/ortilib/osprober.py
itchi/profilerxml/__init__.py
itchi/profilerxml/load.py
itchi/profilerxml/model.py
itchi/profilerxml/save.py
itchi/runnable/__init__.py
itchi/runnable/instrumentation.py
itchi/runnable/program_flow.py
itchi/runningtask/__init__.py
itchi/runningtask/basic.py
itchi/runningtask/btf.py
itchi/runningtask/ksar.py
itchi/runningtask/sampling.py
itchi/spinlock/__init__.py
itchi/spinlock/instrumentation_microsar.py
itchi/swat/__init__.py
itchi/swat/encoding.py
itchi/swat/render.py
itchi/swat/runnable_microsar.py
itchi/swat/signals.py
itchi/swat/state.py
itchi/swat/swat.py
itchi/swat/task_state_microsar.py
itchi/swat/version.py
itchi/taskstate/__init__.py
itchi/taskstate/arti.py
itchi/taskstate/complex_inspectors.py
itchi/taskstate/complex_native.py
itchi/taskstate/eb_mk_gen_config_h.py
itchi/taskstate/instrumentation_autocore.py
itchi/taskstate/instrumentation_microsar.py
itchi/taskstate/single_variable.py
itchi/taskstate/thread_mapping_microsar.py
itchi/templates/Eb_Dbg.c
itchi/templates/Eb_Dbg.h
itchi/templates/Os_TimingHooks_arti.c
itchi/templates/Os_TimingHooks_arti.h
itchi/templates/Os_TimingHooks_isystem.c
itchi/templates/Os_TimingHooks_isystem.h
itchi/templates/Os_TimingHooks_swat.h
itchi/templates/Rte_Hook_isystem.template.c
itchi/templates/__init__.py
itchi/templates/render.py
itchi/templates/swat_config.h
itchi-9.21.367.3.dist-info/licenses/LICENSE
itchi-9.21.367.3.dist-info/METADATA
itchi-9.21.367.3.dist-info/WHEEL
itchi-9.21.367.3.dist-info/entry_points.txt
itchi-9.21.367.3.dist-info/top_level.txt
itchi-9.21.367.3.dist-info/RECORD
