Metadata-Version: 2.4
Name: itchi
Version: 9.21.367.3
Summary: TASKING itchi
Author: TASKING Germany GmbH
Project-URL: Homepage, https://www.tasking.com
Project-URL: Support, https://support.tasking.com/T
Classifier: Programming Language :: Python :: 3
Classifier: License :: OSI Approved :: BSD License
Classifier: Operating System :: OS Independent
Requires-Python: >=3.8
License-File: LICENSE
Requires-Dist: Jinja2
Requires-Dist: pydantic
Requires-Dist: PySide6
Provides-Extra: dev
Requires-Dist: mypy; extra == "dev"
Dynamic: license-file
